MANIFEST.in
README.md
setup.cfg
setup.py
ml4s/VERSION
ml4s/__init__.py
ml4s/_troubleshoot.py
ml4s/nn.py
ml4s.egg-info/PKG-INFO
ml4s.egg-info/SOURCES.txt
ml4s.egg-info/dependency_links.txt
ml4s.egg-info/requires.txt
ml4s.egg-info/top_level.txt
ml4s/backend/__init__.py
ml4s/backend/_backend.py
ml4s/backend/_dtype.py
ml4s/backend/_linalg.py
ml4s/backend/_linalg_preconditioner.py
ml4s/backend/_minimize.py
ml4s/backend/_numpy_backend.py
ml4s/backend/_object.py
ml4s/backend/_partition.py
ml4s/backend/_profile.py
ml4s/backend/_triangular_wip.py
ml4s/backend/jax/__init__.py
ml4s/backend/jax/_jax_backend.py
ml4s/backend/jax/stax_nets.py
ml4s/backend/tensorflow/__init__.py
ml4s/backend/tensorflow/_compile_cuda.py
ml4s/backend/tensorflow/_profiling.py
ml4s/backend/tensorflow/_tf_backend.py
ml4s/backend/tensorflow/_tf_cuda_resample.py
ml4s/backend/tensorflow/nets.py
ml4s/backend/torch/__init__.py
ml4s/backend/torch/_torch_backend.py
ml4s/backend/torch/nets.py
ml4s/math/__init__.py
ml4s/math/_fit.py
ml4s/math/_functional.py
ml4s/math/_magic_ops.py
ml4s/math/_nd.py
ml4s/math/_ops.py
ml4s/math/_optimize.py
ml4s/math/_shape.py
ml4s/math/_sparse.py
ml4s/math/_tensors.py
ml4s/math/_trace.py
ml4s/math/extrapolation.py
ml4s/math/magic.py