Metadata-Version: 2.1
Name: ml4s
Version: 0.0.2
Summary: Unified API for machine learning
Home-page: https://github.com/holl-/ML4Science
Author: Philipp Holl
Author-email: philipp.holl@tum.de
License: MIT
Download-URL: https://github.com/holl-/ML4Science/archive/0.0.2.tar.gz
Keywords: Machine Learning,Deep Learning,Math,Linear systems,Sparse,Tensor,Named dimensions
Platform: UNKNOWN
Classifier: Development Status :: 5 - Production/Stable
Classifier: Intended Audience :: Developers
Classifier: Topic :: Software Development :: Build Tools
Classifier: License :: OSI Approved :: MIT License
Classifier: Programming Language :: Python :: 3
Classifier: Programming Language :: Python :: 3.6
Classifier: Programming Language :: Python :: 3.7
Classifier: Programming Language :: Python :: 3.8
Classifier: Programming Language :: Python :: 3.9
Classifier: Programming Language :: Python :: 3.10
Classifier: Programming Language :: Python :: 3.11
